{
	"ImportPath": "github.com/Shopify/google_apps",
	"GoVersion": "go1.6",
	"GodepVersion": "v62",
	"Deps": [
		{
			"ImportPath": "github.com/akavel/go-openid",
			"Rev": "5021f800d0de96bc42ad5a646556e683b57c3342"
		},
		{
			"ImportPath": "github.com/gorilla/context",
			"Rev": "14f550f51af52180c2eefed15e5fd18d63c0a64a"
		},
		{
			"ImportPath": "github.com/gorilla/securecookie",
			"Comment": "v1.1",
			"Rev": "667fe4e3466a040b780561fe9b51a83a3753eefc"
		},
		{
			"ImportPath": "github.com/gorilla/sessions",
			"Rev": "a1216e0aed834aa9074063dd4085f5c3df8d1fab"
		}
	]
}
